onneggs/__init__.py
onneggs/__main__.py
onneggs/convert_to_egg.py
onneggs/convert_to_onnx.py
onneggs/egg_conversion_strategies.py
onneggs/folder.py
onneggs/folding_test_generator.py
onneggs/helpers.py
onneggs/onnx_tracking.py
onneggs/singleton_hell.py
onneggs-1.0.0.dist-info/METADATA
onneggs-1.0.0.dist-info/WHEEL
onneggs-1.0.0.dist-info/RECORD
