Metadata-Version: 2.3
Name: onneggs
Version: 1.0.0
Requires-Python: >=3.10
Requires-Dist: click
Requires-Dist: eggwrap
Requires-Dist: maturin
Requires-Dist: numpy
Requires-Dist: onnx
Requires-Dist: onnxruntime
